README.rst
setup.cfg
setup.py
deadjson/__init__.py
deadjson/config.py
deadjson.egg-info/PKG-INFO
deadjson.egg-info/SOURCES.txt
deadjson.egg-info/dependency_links.txt
deadjson.egg-info/top_level.txt