Metadata-Version: 1.1
Name: deadjson
Version: 1.0.5
Summary: A Python library implementing a dict-like object that writes to a JSON file as it is modified
Home-page: https://github.com/adityanugraha98/deadjson
Author: ADITYA NUGRAHA
Author-email: adityana987@gmail.com
License: MIT
Project-URL: Bug Reports, https://github.com/adityanugraha98/deadjson/issues
Platform: UNKNOWN
Classifier: Development Status :: 5 - Production/Stable
Classifier: Intended Audience :: Developers
Classifier: Topic :: Games/Entertainment
Classifier: Topic :: Utilities
Classifier: Topic :: Software Development :: Libraries :: Python Modules
Classifier: License :: OSI Approved :: MIT License
Classifier: Programming Language :: Python :: 2.7
Classifier: Programming Language :: Python :: 3
Classifier: Programming Language :: Python :: 3.4
Classifier: Programming Language :: Python :: 3.5
Classifier: Programming Language :: Python :: 3.6
